{
  "total_count": 1200,
  "incomplete_results": false,
  "items": [
    {
      "login": "bambang",
      "id": 208899,
      "node_id": "MDQ6VXNlcjIwODg5OQ==",
      "avatar_url": "https://avatars.githubusercontent.com/u/208899?v=4",
      "gravatar_id": "",
      "url": "https://api.github.com/users/bambang",
      "html_url": "https://github.com/bambang",
      "followers_url": "https://api.github.com/users/bambang/followers",
      "following_url": "https://api.github.com/users/bambang/following{/other_user}",
      "gists_url": "https://api.github.com/users/bambang/gists{/gist_id}",
      "starred_url": "https://api.github.com/users/bambang/starred{/owner}{/repo}",
      "subscriptions_url": "https://api.github.com/users/bambang/subscriptions",
      "organizations_url": "https://api.github.com/users/bambang/orgs",
      "repos_url": "https://api.github.com/users/bambang/repos",
      "events_url": "https://api.github.com/users/bambang/events{/privacy}",
      "received_events_url": "https://api.github.com/users/bambang/received_events",
      "type": "User",
      "site_admin": false,
      "score": 1
    },
    {
      "login": "BambangHeriSetiawan",
      "id": 5673981,
      "node_id": "MDQ6VXNlcjU2NzM5ODE=",
      "avatar_url": "https://avatars.githubusercontent.com/u/5673981?v=4",
      "gravatar_id": "",
      "url": "https://api.github.com/users/BambangHeriSetiawan",
      "html_url": "https://github.com/BambangHeriSetiawan",
      "followers_url": "https://api.github.com/users/BambangHeriSetiawan/followers",
      "following_url": "https://api.github.com/users/BambangHeriSetiawan/following{/other_user}",
      "gists_url": "https://api.github.com/users/BambangHeriSetiawan/gists{/gist_id}",
      "starred_url": "https://api.github.com/users/BambangHeriSetiawan/starred{/owner}{/repo}",
      "subscriptions_url": "https://api.github.com/users/BambangHeriSetiawan/subscriptions",
      "organizations_url": "https://api.github.com/users/BambangHeriSetiawan/orgs",
      "repos_url": "https://api.github.com/users/BambangHeriSetiawan/repos",
      "events_url": "https://api.github.com/users/BambangHeriSetiawan/events{/privacy}",
      "received_events_url": "https://api.github.com/users/BambangHeriSetiawan/received_events",
      "type": "User",
      "site_admin": false,
      "score": 1
    },
    {
      "login": "bpdp",
      "id": 654252,
      "node_id": "MDQ6VXNlcjY1NDI1Mg==",
      "avatar_url": "https://avatars.githubusercontent.com/u/654252?v=4",
      "gravatar_id": "",
      "url": "https://api.github.com/users/bpdp",
      "html_url": "https://github.com/bpdp",
      "followers_url": "https://api.github.com/users/bpdp/followers",
      "following_url": "https://api.github.com/users/bpdp/following{/other_user}",
      "gists_url": "https://api.github.com/users/bpdp/gists{/gist_id}",
      "starred_url": "https://api.github.com/users/bpdp/starred{/owner}{/repo}",
      "subscriptions_url": "https://api.github.com/users/bpdp/subscriptions",
      "organizations_url": "https://api.github.com/users/bpdp/orgs",
      "repos_url": "https://api.github.com/users/bpdp/repos",
      "events_url": "https://api.github.com/users/bpdp/events{/privacy}",
      "received_events_url": "https://api.github.com/users/bpdp/received_events",
      "type": "User",
      "site_admin": false,
      "score": 1
    },
    {
      "login": "bamsarts",
      "id": 11385796,
      "node_id": "MDQ6VXNlcjExMzg1Nzk2",
      "avatar_url": "https://avatars.githubusercontent.com/u/11385796?v=4",
      "gravatar_id": "",
      "url": "https://api.github.com/users/bamsarts",
      "html_url": "https://github.com/bamsarts",
      "followers_url": "https://api.github.com/users/bamsarts/followers",
      "following_url": "https://api.github.com/users/bamsarts/following{/other_user}",
      "gists_url": "https://api.github.com/users/bamsarts/gists{/gist_id}",
      "starred_url": "https://api.github.com/users/bamsarts/starred{/owner}{/repo}",
      "subscriptions_url": "https://api.github.com/users/bamsarts/subscriptions",
      "organizations_url": "https://api.github.com/users/bamsarts/orgs",
      "repos_url": "https://api.github.com/users/bamsarts/repos",
      "events_url": "https://api.github.com/users/bamsarts/events{/privacy}",
      "received_events_url": "https://api.github.com/users/bamsarts/received_events",
      "type": "User",
      "site_admin": false,
      "score": 1
    },
    {
      "login": "Bambangsolehudin",
      "id": 42888942,
      "node_id": "MDQ6VXNlcjQyODg4OTQy",
      "avatar_url": "https://avatars.githubusercontent.com/u/42888942?v=4",
      "gravatar_id": "",
      "url": "https://api.github.com/users/Bambangsolehudin",
      "html_url": "https://github.com/Bambangsolehudin",
      "followers_url": "https://api.github.com/users/Bambangsolehudin/followers",
      "following_url": "https://api.github.com/users/Bambangsolehudin/following{/other_user}",
      "gists_url": "https://api.github.com/users/Bambangsolehudin/gists{/gist_id}",
      "starred_url": "https://api.github.com/users/Bambangsolehudin/starred{/owner}{/repo}",
      "subscriptions_url": "https://api.github.com/users/Bambangsolehudin/subscriptions",
      "organizations_url": "https://api.github.com/users/Bambangsolehudin/orgs",
      "repos_url": "https://api.github.com/users/Bambangsolehudin/repos",
      "events_url": "https://api.github.com/users/Bambangsolehudin/events{/privacy}",
      "received_events_url": "https://api.github.com/users/Bambangsolehudin/received_events",
      "type": "User",
      "site_admin": false,
      "score": 1
    },
    {
      "login": "oldstager",
      "id": 30562774,
      "node_id": "MDQ6VXNlcjMwNTYyNzc0",
      "avatar_url": "https://avatars.githubusercontent.com/u/30562774?v=4",
      "gravatar_id": "",
      "url": "https://api.github.com/users/oldstager",
      "html_url": "https://github.com/oldstager",
      "followers_url": "https://api.github.com/users/oldstager/followers",
      "following_url": "https://api.github.com/users/oldstager/following{/other_user}",
      "gists_url": "https://api.github.com/users/oldstager/gists{/gist_id}",
      "starred_url": "https://api.github.com/users/oldstager/starred{/owner}{/repo}",
      "subscriptions_url": "https://api.github.com/users/oldstager/subscriptions",
      "organizations_url": "https://api.github.com/users/oldstager/orgs",
      "repos_url": "https://api.github.com/users/oldstager/repos",
      "events_url": "https://api.github.com/users/oldstager/events{/privacy}",
      "received_events_url": "https://api.github.com/users/oldstager/received_events",
      "type": "User",
      "site_admin": false,
      "score": 1
    },
    {
      "login": "MBambangSumantri",
      "id": 57070723,
      "node_id": "MDQ6VXNlcjU3MDcwNzIz",
      "avatar_url": "https://avatars.githubusercontent.com/u/57070723?v=4",
      "gravatar_id": "",
      "url": "https://api.github.com/users/MBambangSumantri",
      "html_url": "https://github.com/MBambangSumantri",
      "followers_url": "https://api.github.com/users/MBambangSumantri/followers",
      "following_url": "https://api.github.com/users/MBambangSumantri/following{/other_user}",
      "gists_url": "https://api.github.com/users/MBambangSumantri/gists{/gist_id}",
      "starred_url": "https://api.github.com/users/MBambangSumantri/starred{/owner}{/repo}",
      "subscriptions_url": "https://api.github.com/users/MBambangSumantri/subscriptions",
      "organizations_url": "https://api.github.com/users/MBambangSumantri/orgs",
      "repos_url": "https://api.github.com/users/MBambangSumantri/repos",
      "events_url": "https://api.github.com/users/MBambangSumantri/events{/privacy}",
      "received_events_url": "https://api.github.com/users/MBambangSumantri/received_events",
      "type": "User",
      "site_admin": false,
      "score": 1
    },
    {
      "login": "BambangSarwoko",
      "id": 36152378,
      "node_id": "MDQ6VXNlcjM2MTUyMzc4",
      "avatar_url": "https://avatars.githubusercontent.com/u/36152378?v=4",
      "gravatar_id": "",
      "url": "https://api.github.com/users/BambangSarwoko",
      "html_url": "https://github.com/BambangSarwoko",
      "followers_url": "https://api.github.com/users/BambangSarwoko/followers",
      "following_url": "https://api.github.com/users/BambangSarwoko/following{/other_user}",
      "gists_url": "https://api.github.com/users/BambangSarwoko/gists{/gist_id}",
      "starred_url": "https://api.github.com/users/BambangSarwoko/starred{/owner}{/repo}",
      "subscriptions_url": "https://api.github.com/users/BambangSarwoko/subscriptions",
      "organizations_url": "https://api.github.com/users/BambangSarwoko/orgs",
      "repos_url": "https://api.github.com/users/BambangSarwoko/repos",
      "events_url": "https://api.github.com/users/BambangSarwoko/events{/privacy}",
      "received_events_url": "https://api.github.com/users/BambangSarwoko/received_events",
      "type": "User",
      "site_admin": false,
      "score": 1
    },
    {
      "login": "aribambang",
      "id": 10102342,
      "node_id": "MDQ6VXNlcjEwMTAyMzQy",
      "avatar_url": "https://avatars.githubusercontent.com/u/10102342?v=4",
      "gravatar_id": "",
      "url": "https://api.github.com/users/aribambang",
      "html_url": "https://github.com/aribambang",
      "followers_url": "https://api.github.com/users/aribambang/followers",
      "following_url": "https://api.github.com/users/aribambang/following{/other_user}",
      "gists_url": "https://api.github.com/users/aribambang/gists{/gist_id}",
      "starred_url": "https://api.github.com/users/aribambang/starred{/owner}{/repo}",
      "subscriptions_url": "https://api.github.com/users/aribambang/subscriptions",
      "organizations_url": "https://api.github.com/users/aribambang/orgs",
      "repos_url": "https://api.github.com/users/aribambang/repos",
      "events_url": "https://api.github.com/users/aribambang/events{/privacy}",
      "received_events_url": "https://api.github.com/users/aribambang/received_events",
      "type": "User",
      "site_admin": false,
      "score": 1
    },
    {
      "login": "sirnobrain",
      "id": 24495789,
      "node_id": "MDQ6VXNlcjI0NDk1Nzg5",
      "avatar_url": "https://avatars.githubusercontent.com/u/24495789?v=4",
      "gravatar_id": "",
      "url": "https://api.github.com/users/sirnobrain",
      "html_url": "https://github.com/sirnobrain",
      "followers_url": "https://api.github.com/users/sirnobrain/followers",
      "following_url": "https://api.github.com/users/sirnobrain/following{/other_user}",
      "gists_url": "https://api.github.com/users/sirnobrain/gists{/gist_id}",
      "starred_url": "https://api.github.com/users/sirnobrain/starred{/owner}{/repo}",
      "subscriptions_url": "https://api.github.com/users/sirnobrain/subscriptions",
      "organizations_url": "https://api.github.com/users/sirnobrain/orgs",
      "repos_url": "https://api.github.com/users/sirnobrain/repos",
      "events_url": "https://api.github.com/users/sirnobrain/events{/privacy}",
      "received_events_url": "https://api.github.com/users/sirnobrain/received_events",
      "type": "User",
      "site_admin": false,
      "score": 1
    }
  ]
}